anyai/__init__.py
anyocr-0.0.1.dist-info/LICENSE
anyocr-0.0.1.dist-info/METADATA
anyocr-0.0.1.dist-info/WHEEL
anyocr-0.0.1.dist-info/top_level.txt
anyocr-0.0.1.dist-info/RECORD
